django_breeze/__init__.py
django_breeze/__main__.py
django_breeze/apps.py
django_breeze/core/__init__.py
django_breeze/core/handlers/__init__.py
django_breeze/core/handlers/files.py
django_breeze/core/management/__init__.py
django_breeze/core/management/commands/_remove-app.py
django_breeze/core/management/commands/create-app.py
django_breeze/core/management/commands/startapp.py
django_breeze/core/management/commands/startproject.py
django_breeze/core/utils.py
django_breeze/middleware.py
django_breeze/scripts/django_breeze.py
django_breeze/settings.py
django_breeze/static/django_breeze/django-breeze-logo.jpg
django_breeze/static/django_breeze/django-breeze-logo.png
django_breeze/templates/react/.gitignore
django_breeze/templates/react/package.json
django_breeze/templates/react/postcss.config.js
django_breeze/templates/react/src/Layout/SiteLayout.jsx
django_breeze/templates/react/src/assets/react.svg
django_breeze/templates/react/src/index.css
django_breeze/templates/react/src/index.html
django_breeze/templates/react/src/main.jsx
django_breeze/templates/react/src/pages/index.jsx
django_breeze/templates/react/tailwind.config.js
django_breeze/templates/react/vite.config.js
django_breeze/templates/react_typescript/.gitignore
django_breeze/templates/react_typescript/package.json
django_breeze/templates/react_typescript/postcss.config.js
django_breeze/templates/react_typescript/public/vite.svg
django_breeze/templates/react_typescript/src/Layout/SiteLayout.tsx
django_breeze/templates/react_typescript/src/assets/react.svg
django_breeze/templates/react_typescript/src/index.css
django_breeze/templates/react_typescript/src/index.html
django_breeze/templates/react_typescript/src/main.tsx
django_breeze/templates/react_typescript/src/pages/index.tsx
django_breeze/templates/react_typescript/src/vite-env.d.ts
django_breeze/templates/react_typescript/tailwind.config.js
django_breeze/templates/react_typescript/tsconfig.json
django_breeze/templates/react_typescript/tsconfig.node.json
django_breeze-1.1.0.dist-info/LICENSE.md
django_breeze-1.1.0.dist-info/METADATA
django_breeze-1.1.0.dist-info/WHEEL
django_breeze-1.1.0.dist-info/entry_points.txt
django_breeze-1.1.0.dist-info/RECORD
