Metadata-Version: 2.1
Name: django-breeze
Version: 1.1.0
Summary: Django Breeze provides a minimal and simple starting point for building a Django application with Inertia and Vite with minimal or no configuration. Styled with Tailwind CSS.
Home-page: https://github.com/Louxsdon/django-breeze
License: MIT
Keywords: react,django,vue,inertia,vite
Author: louxsdon
Author-email: louisayivi.dev@gmail.com
Requires-Python: >=3.10,<4.0
Classifier: License :: OSI Approved :: MIT License
Classifier: Programming Language :: Python :: 3
Classifier: Programming Language :: Python :: 3.10
Classifier: Programming Language :: Python :: 3.11
Classifier: Programming Language :: Python :: 3.12
Classifier: Programming Language :: Python :: 3.13
Requires-Dist: django-vite (==3.0.5)
Requires-Dist: inertia-django (==0.6.0)
Project-URL: Repository, https://github.com/Louxsdon/django-breeze
